{"__symbolic":"module","version":4,"metadata":{"NgxRansackService":{"__symbolic":"class","decorators":[{"__symbolic":"call","expression":{"__symbolic":"reference","module":"@angular/core","name":"Injectable","line":6,"character":1},"arguments":[{"providedIn":"root"}]}],"members":{"__ctor__":[{"__symbolic":"constructor"}],"toRansack":[{"__symbolic":"method"}],"_setParam":[{"__symbolic":"method"}],"_kebabStr":[{"__symbolic":"method"}]},"statics":{"ɵprov":{}}}},"origins":{"NgxRansackService":"./lib/ngx-ransack.service"},"importAs":"ngx-ransack"}